<?xml version="1.0" encoding="utf-8" standalone="yes"?>
<InfoWarnings>
  <Info>07/23/2012 14:11:58 Begin full analysis with NDepend v4.0.2</Info>
  <Info>No Baseline for Comparison loaded.</Info>
  <Info>Serial mode</Info>
  <Info>Assemblies loaded from {C:\Windows\Microsoft.NET\Framework\v4.0.30319} 
   mscorlib.dll   v4.0.0.0
   System.Web.dll   v4.0.0.0
   System.Web.Extensions.dll   v4.0.0.0
   System.dll   v4.0.0.0</Info>
  <Warning>No application or third party assembly found in directory {C:\Windows\Microsoft.NET\Framework\v4.0.30319\WPF}</Warning>
  <Info>Assemblies loaded from {C:\Desarrollo\MSBuildProject\MSBuildProjectWeb\bin} 
   MSBuildProjectWeb.dll   v1.0.0.0</Info>
  <Info>Assemblies loaded from {C:\Desarrollo\MSBuildProject\MSBuildProjectClass\bin\Debug} 
   MSBuildProjectClass.dll   v1.0.0.0</Info>
  <Info>Assemblies loaded from {C:\Desarrollo\MSBuildProject\MSBuildProjectTest\bin\Debug} 
   MSBuildProjectTest.dll   v1.0.0.0
   nunit.framework.dll   v2.6.0.12051</Info>
  <Info>20 source files parsed ; all source files found ; all source files in-sync with PDB</Info>
  <Info>0 code rule has been extracted from code.</Info>
  <Info>No dependency cycle detected in assemblies referencement graph.</Info>
  <Info>07/23/2012 14:12:03 Analyse dependencies of your application.</Info>
  <Info>07/23/2012 14:12:04 Building the report (standard).</Info>
</InfoWarnings>